Metadata-Version: 2.1
Name: pms5003-micropython
Version: 0.0.7
Summary: MicroPython library for the Plantower PMS5003 Particulate Matter Sensor.
Home-page: https://www.pimoroni.com
Author: Philip Howard
Author-email: phil@pimoroni.com
License: MIT
Project-URL: github, https://github.com/pimoroni/pms5003-micropython
Keywords: micropython,electronics
Platform: UNKNOWN
Classifier: Development Status :: 1 - Planning
Classifier: Intended Audience :: Developers
Classifier: Programming Language :: Python :: Implementation :: MicroPython
